LICENSE.txt
MANIFEST.in
PROJECT.txt
README.rst
setup.py
docs/quickstart.rst
edi/__init__.py
edi/default_editor.py
edi/edi_command.py
edi/interpreter.py
edi/parent_checker.py
edi/whichfiles.py
edi/yaml_config.py
edi.egg-info/PKG-INFO
edi.egg-info/SOURCES.txt
edi.egg-info/dependency_links.txt
edi.egg-info/entry_points.txt
edi.egg-info/not-zip-safe
edi.egg-info/requires.txt
edi.egg-info/top_level.txt