Metadata-Version: 1.1
Name: edi
Version: 0.6
Summary: A tool for quickly opening files deep in your git repo with a minimum of keystrokes.
Home-page: https://edi.readthedocs.org/
Author: Colm O'Connor
Author-email: colm.oconnor.github@gmail.com
License: MIT
Keywords: development environment tool git find files editor
Platform: UNKNOWN
Classifier: Development Status :: 3 - Alpha
Classifier: Intended Audience :: Developers
Classifier: License :: OSI Approved :: MIT License
Classifier: Topic :: Software Development :: Build Tools
Classifier: Programming Language :: Python :: 2
Classifier: Programming Language :: Python :: 2.6
Classifier: Programming Language :: Python :: 2.7
